pycman/__init__.py
pycman/__main__.py
pycman/cli.py
pycman/core/__init__.py
pycman/core/initializer.py
pycman/core/builders/git_builder.py
pycman/core/builders/package_module_builder.py
pycman/core/builders/prb_builder.py
pycman/core/builders/readme_builder.py
pycman/core/builders/requirements_builder.py
pycman/core/builders/tests_builder.py
pycman/utils/__init__.py
pycman/utils/common.py
pycman/utils/logo.py
pycman/utils/version.py
pycman-1.1.1.dist-info/AUTHORS
pycman-1.1.1.dist-info/METADATA
pycman-1.1.1.dist-info/WHEEL
pycman-1.1.1.dist-info/entry_points.txt
pycman-1.1.1.dist-info/pbr.json
pycman-1.1.1.dist-info/top_level.txt
pycman-1.1.1.dist-info/RECORD
