Metadata-Version: 2.1
Name: pycman
Version: 1.1.1
Summary: Python package manager
Home-page: https://github.com/Singein/Pycman
Author: Singein Zhang
Author-email: singein@outlook.com
License: MIT
Platform: UNKNOWN
Requires-Python: >= 3.6
Requires-Dist: fire (>=0.2.1)
Requires-Dist: wheel
Requires-Dist: commitizen
Requires-Dist: pbr
Requires-Dist: pytest
Requires-Dist: pytest-xdist
Requires-Dist: pytest-sugar
Requires-Dist: pytest-html
